qcrandom/__init__.py
qcrandom/qcrandom.py
qcrandom-0.3.post1.dist-info/LICENSE
qcrandom-0.3.post1.dist-info/METADATA
qcrandom-0.3.post1.dist-info/WHEEL
qcrandom-0.3.post1.dist-info/top_level.txt
qcrandom-0.3.post1.dist-info/RECORD
