Metadata-Version: 2.1
Name: qcrandom
Version: 0.3.post1
Summary: qcrandom is a python library which provides easy way to generate random numbers on quantum computers.
Home-page: https://github.com/pk8868/qc-random/
Author: Pawel Kromka, Jakub Wtorkiewicz
Author-email: pawel.kromka.05@onet.eu, kuba.wtorkiewicz@gmail.com
License: UNKNOWN
Project-URL: Bug Tracker, https://github.com/pk8868/qc-random/issues
Keywords: python,random,quantum
Platform: UNKNOWN
Classifier: Programming Language :: Python :: 3
Classifier: License :: OSI Approved :: MIT License
Requires-Python: >=3.7
License-File: LICENSE
Requires-Dist: qiskit
